chileanrutify/__init__.py
chileanrutify/chileanrutify.py
chileanrutify/rutfunctions.py
chileanrutify-0.2.0.dist-info/LICENSE
chileanrutify-0.2.0.dist-info/METADATA
chileanrutify-0.2.0.dist-info/WHEEL
chileanrutify-0.2.0.dist-info/top_level.txt
chileanrutify-0.2.0.dist-info/RECORD
