Metadata-Version: 2.1
Name: chileanrutify
Version: 0.2.0
Summary: Chilean rut Python package - Chilean Rut/Run validator and formatter library
Author: mihailpozarski
Author-email: Mihail Pozarski <mihailpozarski@outlook.com>
Maintainer-email: Mihail Pozarski <mihailpozarski@outlook.com>
License: MIT License
Project-URL: Repository, https://github.com/mihailpozarski/chilean-rutify-py
Keywords: python,library,package,chile,chilean,rut,chilean-rut,chilean-rut-utils,chilean-rutify,chilean-id
Classifier: Development Status :: 5 - Production/Stable
Classifier: Intended Audience :: Developers
Classifier: License :: OSI Approved :: MIT License
Classifier: Programming Language :: Python :: 3
Requires-Python: >=3.0
License-File: LICENSE
